sqstaskmaster/__init__.py
sqstaskmaster/message_handler.py
sqstaskmaster/task_manager.py
sqstaskmaster/version.py
sqstaskmaster/tests/__init__.py
sqstaskmaster/tests/test_message_handler.py
sqstaskmaster/tests/test_task_manager.py
sqstaskmaster-0.0.1.dist-info/LICENSE
sqstaskmaster-0.0.1.dist-info/METADATA
sqstaskmaster-0.0.1.dist-info/WHEEL
sqstaskmaster-0.0.1.dist-info/top_level.txt
sqstaskmaster-0.0.1.dist-info/RECORD
