Metadata-Version: 2.1
Name: sqstaskmaster
Version: 0.0.1
Summary: SQS Task Master for unwieldy python data processing by Upserve
Home-page: https://github.com/upserve/sqstaskmaster
Author: Upserve
Author-email: datascience@upserve.com
License: UNKNOWN
Platform: UNKNOWN
Classifier: Programming Language :: Python :: 3
Classifier: License :: OSI Approved :: MIT License
Classifier: Operating System :: OS Independent
Requires-Python: ~=3.7
Requires-Dist: boto3
Requires-Dist: botocore
Provides-Extra: dev
Requires-Dist: callee ; extra == 'dev'
Requires-Dist: flake8 ; extra == 'dev'
Requires-Dist: black ; extra == 'dev'
